google_civic_information_api/__init__.py
google_civic_information_api/constants.py
google_civic_information_api/divisions.py
google_civic_information_api/elections.py
google_civic_information_api/representatives.py
google_civic_information_api-1.0.0.dist-info/LICENSE
google_civic_information_api-1.0.0.dist-info/METADATA
google_civic_information_api-1.0.0.dist-info/WHEEL
google_civic_information_api-1.0.0.dist-info/top_level.txt
google_civic_information_api-1.0.0.dist-info/RECORD
