Metadata-Version: 2.1
Name: google-civic-information-api
Version: 1.0.0
Summary: A python wrapper for Google's Civic Information API
Author: Matthew Mathur
License: BSD 3-Clause License
Project-URL: Homepage, https://github.com/k0pak4/google-civic-information-api-py
Keywords: civic-information-api
Classifier: License :: OSI Approved :: BSD License
Classifier: Programming Language :: Python :: 3
Requires-Python: >=3.7
License-File: LICENSE
Requires-Dist: requests (>=2.1.0)
Provides-Extra: dev
Requires-Dist: pytest ; extra == 'dev'
